README.txt
setup.py
zopeskel.txt
collective/__init__.py
collective/__init__.pyc
collective.volunteer.egg-info/PKG-INFO
collective.volunteer.egg-info/SOURCES.txt
collective.volunteer.egg-info/dependency_links.txt
collective.volunteer.egg-info/entry_points.txt
collective.volunteer.egg-info/namespace_packages.txt
collective.volunteer.egg-info/not-zip-safe
collective.volunteer.egg-info/paster_plugins.txt
collective.volunteer.egg-info/requires.txt
collective.volunteer.egg-info/top_level.txt
collective/volunteer/__init__.py
collective/volunteer/__init__.pyc
collective/volunteer/config.py
collective/volunteer/config.pyc
collective/volunteer/configure.zcml
collective/volunteer/tests.py
collective/volunteer/validators.py
collective/volunteer/validators.pyc
collective/volunteer/version.txt
collective/volunteer/browser/__init__.py
collective/volunteer/browser/__init__.pyc
collective/volunteer/browser/configure.zcml
collective/volunteer/browser/export.py
collective/volunteer/browser/export.pyc
collective/volunteer/browser/volunteer.css
collective/volunteer/browser/volunteer.js
collective/volunteer/browser/volunteerday.py
collective/volunteer/browser/volunteerday.pyc
collective/volunteer/browser/volunteerday_view.pt
collective/volunteer/content/__init__.py
collective/volunteer/content/__init__.pyc
collective/volunteer/content/interfaces.py
collective/volunteer/content/interfaces.pyc
collective/volunteer/content/volunteerday.py
collective/volunteer/content/volunteerday.pyc
collective/volunteer/profiles/default/cssregistry.xml
collective/volunteer/profiles/default/factorytool.xml
collective/volunteer/profiles/default/jsregistry.xml
collective/volunteer/profiles/default/types.xml
collective/volunteer/profiles/default/types/VolunteerDay.xml
docs/HISTORY.txt
docs/INSTALL.txt
docs/LICENSE.GPL
docs/LICENSE.txt