Metadata-Version: 1.0
Name: collective.volunteer
Version: 1.03
Summary: a product that can manage volunteering.
Home-page: http://svn.plone.org/svn/plone/plone.example
Author: Nathan Van Gheem
Author-email: vangheem@gmail.com
License: GPL
Platform: UNKNOWN
Classifier: Framework :: Plone
Classifier: Programming Language :: Python
Classifier: Topic :: Software Development :: Libraries :: Python Modules
